tests/__init__.py
tests/common/__init__.py
tests/common/utils.py
tests/integration/__init__.py
tests/integration/conftest.py
tests/integration/test_xero.py
xerosdk/__init__.py
xerosdk/exceptions.py
xerosdk/xerosdk.py
xerosdk/apis/__init__.py
xerosdk/apis/accounts.py
xerosdk/apis/api_base.py
xerosdk/apis/attachments.py
xerosdk/apis/bank_transactions.py
xerosdk/apis/connections.py
xerosdk/apis/contacts.py
xerosdk/apis/currencies.py
xerosdk/apis/invoices.py
xerosdk/apis/items.py
xerosdk/apis/linked_transactions.py
xerosdk/apis/organisations.py
xerosdk/apis/payments.py
xerosdk/apis/tax_rates.py
xerosdk/apis/tenants.py
xerosdk/apis/tracking_categories.py
xerosdk-0.14.3.dist-info/LICENSE
xerosdk-0.14.3.dist-info/METADATA
xerosdk-0.14.3.dist-info/WHEEL
xerosdk-0.14.3.dist-info/top_level.txt
xerosdk-0.14.3.dist-info/RECORD
