Metadata-Version: 2.2
Name: xerosdk
Version: 0.14.3
Summary: Python SDK to access Xero APIs
Home-page: https://github.com/fylein/xero-sdk-py
Author: Ashwin T
Author-email: ashwin.t@fyle.in
License: MIT
Keywords: xero,api,python,sdk
Classifier: Topic :: Internet :: WWW/HTTP
Classifier: Intended Audience :: Developers
Classifier: Programming Language :: Python :: 3
Classifier: License :: OSI Approved :: MIT License
Classifier: Operating System :: OS Independent
License-File: LICENSE
Requires-Dist: requests==2.32.3
Dynamic: author
Dynamic: author-email
Dynamic: classifier
Dynamic: description
Dynamic: description-content-type
Dynamic: home-page
Dynamic: keywords
Dynamic: license
Dynamic: requires-dist
Dynamic: summary
